lwproxy/__init__.py
lwproxy/lwproxy.py
lw_trv_proxy-0.6.2.dist-info/LICENSE.md
lw_trv_proxy-0.6.2.dist-info/METADATA
lw_trv_proxy-0.6.2.dist-info/WHEEL
lw_trv_proxy-0.6.2.dist-info/entry_points.txt
lw_trv_proxy-0.6.2.dist-info/top_level.txt
lw_trv_proxy-0.6.2.dist-info/RECORD
