Metadata-Version: 2.1
Name: lw-trv-proxy
Version: 0.6.2
Summary: A Lightwave RF Proxy
Home-page: https://github.com/ColinRobbins/Homeassistant-Lightwave-TRV
Author: Colin Robbins
Author-email: colin.john.robbins@gmail.com
License: UNKNOWN
Platform: UNKNOWN
Classifier: Programming Language :: Python :: 3
Classifier: License :: OSI Approved :: MIT License
Classifier: Operating System :: OS Independent
Requires-Python: >=3.6
